setup.py
shiyan_test/__init__.py
shiyan_test/shiyan.py
shiyan_test.egg-info/PKG-INFO
shiyan_test.egg-info/SOURCES.txt
shiyan_test.egg-info/dependency_links.txt
shiyan_test.egg-info/top_level.txt