Metadata-Version: 1.0
Name: shiyan-test
Version: 0.0.1
Summary: shiyan test sdk
Home-page: http://yanyan.tech
Author: Yan Shi
Author-email: shiyanaimama@163.com
License: MIT Licence
Keywords: pip,shiyan,test
Platform: any
